TayTools/__init__.py
TayTools/configure.py
TayTools/tools.py
TayTules_pkg_taytek-0.1.0.dist-info/METADATA
TayTules_pkg_taytek-0.1.0.dist-info/WHEEL
TayTules_pkg_taytek-0.1.0.dist-info/top_level.txt
TayTules_pkg_taytek-0.1.0.dist-info/RECORD
