Metadata-Version: 2.1
Name: TayTules-pkg-taytek
Version: 0.1.0
Summary: A set of tools made by me!
Home-page: https://github.com/pypa/sampleproject
Author: taytek
Author-email: taylor.kerrihard@gmail.com
License: UNKNOWN
Project-URL: Bug Tracker, https://github.com/pypa/sampleproject/issues
Platform: UNKNOWN
Classifier: Programming Language :: Python :: 3
Classifier: License :: OSI Approved :: MIT License
Classifier: Operating System :: OS Independent
Requires-Python: >=3.6
